ginz/__init__.py
ginz/__main__.py
ginz/tree.py
ginz-1.3.dist-info/LICENSE
ginz-1.3.dist-info/METADATA
ginz-1.3.dist-info/WHEEL
ginz-1.3.dist-info/top_level.txt
ginz-1.3.dist-info/RECORD
