Metadata-Version: 2.1
Name: ginz
Version: 1.3
Summary: Ginz is a command-line utility that simplifies the process of cloning multiple repositories from GitHub by allowing you to specify the repositories and their branches in a single configuration file.
Home-page: https://github.com/happer64bit/ginz-cli
Author: Happer64Bit
Author-email: happer64bit@gmail.com
License: MIT
License-File: LICENSE
Requires-Dist: toml
Requires-Dist: GitPython
Requires-Dist: colorama
Requires-Dist: tqdm
Requires-Dist: requests
